wells/__init__.py
wells/bashscript_utils.py
wells/config.py
wells/csvutils.py
wells/debug.py
wells/fileutils.py
wells/iputils.py
wells/paramcheck.py
wells/py3utils.py
wells/redisutils.py
wells/shellutils.py
wells/test_bashscript_utils.py
wells/test_config.py
wells/test_csvutils.py
wells/test_debug.py
wells/test_debug_timeit.py
wells/test_iputils.py
wells/test_paramcheck.py
wells/test_redisutils.py
wells/test_shellutils.py
wells/test_utils.py
wells/test_utils_retry.py
wells/utils.py
wells-1.5.0.dist-info/LICENSE
wells-1.5.0.dist-info/METADATA
wells-1.5.0.dist-info/WHEEL
wells-1.5.0.dist-info/top_level.txt
wells-1.5.0.dist-info/RECORD
